LICENSE
MANIFEST.in
README.md
extras_requirements.txt
requirements.txt
setup.cfg
setup.py
versioneer.py
csirtg_smrt/__init__.py
csirtg_smrt/_version.py
csirtg_smrt/archiver.py
csirtg_smrt/constants.py
csirtg_smrt/exceptions.py
csirtg_smrt/fetcher.py
csirtg_smrt/rule.py
csirtg_smrt/smrt.py
csirtg_smrt.egg-info/PKG-INFO
csirtg_smrt.egg-info/SOURCES.txt
csirtg_smrt.egg-info/dependency_links.txt
csirtg_smrt.egg-info/entry_points.txt
csirtg_smrt.egg-info/requires.txt
csirtg_smrt.egg-info/top_level.txt
csirtg_smrt/client/__init__.py
csirtg_smrt/client/dummy.py
csirtg_smrt/client/plugin.py
csirtg_smrt/client/zcif.py
csirtg_smrt/client/zcifv2.py
csirtg_smrt/client/zcifzmq.py
csirtg_smrt/client/zcsirtg.py
csirtg_smrt/client/zelasticsearch.py
csirtg_smrt/client/zsplunk.py
csirtg_smrt/client/zsyslog.py
csirtg_smrt/client/zzmq.py
csirtg_smrt/client/zzyre.py
csirtg_smrt/decoders/__init__.py
csirtg_smrt/decoders/zgzip.py
csirtg_smrt/decoders/zzip.py
csirtg_smrt/parser/__init__.py
csirtg_smrt/parser/bro.py
csirtg_smrt/parser/cef.py
csirtg_smrt/parser/delim.py
csirtg_smrt/parser/pattern.py
csirtg_smrt/parser/pipe.py
csirtg_smrt/parser/semicolon.py
csirtg_smrt/parser/ufw.py
csirtg_smrt/parser/zcifv2.py
csirtg_smrt/parser/zcifv3.py
csirtg_smrt/parser/zcsv.py
csirtg_smrt/parser/zemail.py
csirtg_smrt/parser/zindicator.py
csirtg_smrt/parser/zjson.py
csirtg_smrt/parser/zrss.py
csirtg_smrt/parser/zsmtpd.py
csirtg_smrt/parser/zstix.py
csirtg_smrt/parser/zsyslog.py
csirtg_smrt/parser/ztsv.py
csirtg_smrt/utils/__init__.py
csirtg_smrt/utils/zarrow.py
csirtg_smrt/utils/zcolumns.py
csirtg_smrt/utils/zcontent.py
csirtg_smrt/utils/znltk.py
csirtg_smrt/utils/ztail.py
examples/cifv2.yml
examples/cifv3.yml
examples/csirtg.yml
test/test_nltk.py
test/test_timestamps.py
test/alexa/alexa.yml
test/alexa/alexa_top-1m.csv.zip
test/alienvault/alienvault.yml
test/alienvault/feed.txt
test/bambenek/bambenek.yml
test/bambenek/fqdn_feed.txt
test/bambenek/ipv4_feed.txt
test/csirtg/csirtg.yml
test/csirtg/feed.txt
test/csirtg/feed2_csv.txt
test/malc0de/feed.txt
test/malc0de/malc0de.yml
test/malwaredomains/bulk_registrars.zip
test/malwaredomains/domains.zip
test/malwaredomains/malwaredomains.yml
