Metadata-Version: 1.1
Name: csirtg-smrt
Version: 1.0.5
Summary: s.m.r.t
Home-page: https://github.com/csirtgadgets/csirtg-smrt-py
Author: Wes Young
Author-email: wes@csirtgadgets.org
License: MPL2
Keywords: security
Platform: UNKNOWN
Classifier: Topic :: System :: Networking
Classifier: Environment :: Other Environment
Classifier: Intended Audience :: Developers
Classifier: Programming Language :: Python
